google_oauth2_tool/__init__.py
google_oauth2_tool/__main__.py
google_oauth2_tool-0.0.1.dist-info/LICENSE
google_oauth2_tool-0.0.1.dist-info/METADATA
google_oauth2_tool-0.0.1.dist-info/WHEEL
google_oauth2_tool-0.0.1.dist-info/entry_points.txt
google_oauth2_tool-0.0.1.dist-info/top_level.txt
google_oauth2_tool-0.0.1.dist-info/RECORD
